horton_part/__init__.py
horton_part/__main__.py
horton_part/_version.py
horton_part/alisa.py
horton_part/becke.py
horton_part/gisa.py
horton_part/glisa.py
horton_part/gmbis.py
horton_part/hirshfeld.py
horton_part/hirshfeld_i.py
horton_part/isa.py
horton_part/mbis.py
horton_part/mulliken.py
horton_part/nlis.py
horton_part/utils.py
horton_part/algo/__init__.py
horton_part/algo/cdiis.py
horton_part/algo/diis.py
horton_part/algo/quasi_newton.py
horton_part/core/__init__.py
horton_part/core/base.py
horton_part/core/basis.py
horton_part/core/cache.py
horton_part/core/iterstock.py
horton_part/core/logging.py
horton_part/core/proatomdb.py
horton_part/core/stockholder.py
horton_part/data/constants.yaml
horton_part/data/gauss.json
horton_part/data/gauss.yaml
horton_part/data/keywords.yaml
horton_part/data/part-cube.yaml
horton_part/data/part-dens.yaml
horton_part/data/part-gen.yaml
horton_part/data/slater.json
horton_part/data/slater.yaml
horton_part/scripts/__init__.py
horton_part/scripts/generate_cube.py
horton_part/scripts/generate_density.py
horton_part/scripts/partition_density.py
horton_part/scripts/program.py
horton_part-1.1.8.dist-info/licenses/LICENSE
horton_part-1.1.8.dist-info/METADATA
horton_part-1.1.8.dist-info/WHEEL
horton_part-1.1.8.dist-info/entry_points.txt
horton_part-1.1.8.dist-info/top_level.txt
horton_part-1.1.8.dist-info/RECORD
