Metadata-Version: 2.4
Name: horton-part
Version: 1.1.8
Summary: Molecular partitioning schemes used in computational chemistry
Author-email: YingXing Cheng <yxcheng2buaa@gmail.com>
Maintainer-email: YingXing Cheng <yxcheng2buaa@gmail.com>
License:                    GNU LESSER GENERAL PUBLIC LICENSE
Project-URL: Homepage, https://lisa-partitioning-method.github.io/horton-part/
Project-URL: Repository, https://github.com/LISA-partitioning-method/horton-part
Project-URL: Changelog, https://github.com/LISA-partitioning-method/horton-part/CHANGELOG.md
Keywords: partition schemes,atom-in-moleucle
Classifier: Development Status :: 3 - Alpha
Classifier: Environment :: Console
Classifier: Intended Audience :: Science/Research
Classifier: Intended Audience :: Education
Classifier: Framework :: Matplotlib
Classifier: License :: OSI Approved :: GNU General Public License v3 or later (GPLv3+)
Classifier: Natural Language :: English
Classifier: Operating System :: POSIX
Classifier: Operating System :: MacOS
Classifier: Programming Language :: Python :: 3
Classifier: Programming Language :: Python :: 3.10
Classifier: Programming Language :: Python :: 3.11
Classifier: Programming Language :: Python :: 3.12
Classifier: Programming Language :: Python :: 3.13
Classifier: Topic :: Scientific/Engineering
Requires-Python: >=3.10
License-File: LICENSE
Requires-Dist: quadprog>=0.1.13
Requires-Dist: cvxopt>=1.3.1
Requires-Dist: qpsolvers
Requires-Dist: qc-grid>=0.0.9
Requires-Dist: qc-iodata
Requires-Dist: qc-gbasis>=0.1.0
Requires-Dist: importlib_resources
Requires-Dist: pyyaml
Provides-Extra: dev
Requires-Dist: pre-commit; extra == "dev"
Provides-Extra: tests
Requires-Dist: pytest; extra == "tests"
Requires-Dist: pytest-skip-slow; extra == "tests"
Dynamic: license-file
